ovos_gui_plugin_shell_companion/__init__.py
ovos_gui_plugin_shell_companion/brightness.py
ovos_gui_plugin_shell_companion/color_manager.py
ovos_gui_plugin_shell_companion/descriptions.json
ovos_gui_plugin_shell_companion/helpers.py
ovos_gui_plugin_shell_companion/version.py
ovos_gui_plugin_shell_companion/wigets.py
ovos_gui_plugin_shell_companion/gui/qt5/AdditionalSettings.qml
ovos_gui_plugin_shell_companion/gui/qt5/settings/SettingsModel.qml
ovos_gui_plugin_shell_companion/gui/qt5/settings/ThemeView.qml
ovos_gui_plugin_shell_companion/gui/qt5/settings/about_page.qml
ovos_gui_plugin_shell_companion/gui/qt5/settings/configuration_generator_display.qml
ovos_gui_plugin_shell_companion/gui/qt5/settings/configuration_groups_display.qml
ovos_gui_plugin_shell_companion/gui/qt5/settings/customize_settings.qml
ovos_gui_plugin_shell_companion/gui/qt5/settings/customize_theme.qml
ovos_gui_plugin_shell_companion/gui/qt5/settings/developer_settings.qml
ovos_gui_plugin_shell_companion/gui/qt5/settings/display_settings.qml
ovos_gui_plugin_shell_companion/gui/qt5/settings/factory_settings.qml
ovos_gui_plugin_shell_companion/gui/qt5/settings/homescreen_settings.qml
ovos_gui_plugin_shell_companion/gui/qt5/settings/lupdate-generator.sh
ovos_gui_plugin_shell_companion/gui/qt5/settings/settingspage.qml
ovos_gui_plugin_shell_companion/gui/qt5/settings/ssh_settings.qml
ovos_gui_plugin_shell_companion/gui/qt5/settings/wallpaper_settings.qml
ovos_gui_plugin_shell_companion/gui/qt5/settings/code/colorUtils.js
ovos_gui_plugin_shell_companion/gui/qt5/settings/configuration_ui/settingCheckBox.qml
ovos_gui_plugin_shell_companion/gui/qt5/settings/configuration_ui/settingListBox.qml
ovos_gui_plugin_shell_companion/gui/qt5/settings/configuration_ui/settingTextBox.qml
ovos_gui_plugin_shell_companion/gui/qt5/settings/delegates/BrightnessSlider.qml
ovos_gui_plugin_shell_companion/gui/qt5/settings/delegates/ColorSelectPrimary.qml
ovos_gui_plugin_shell_companion-1.0.6.dist-info/licenses/LICENSE
ovos_gui_plugin_shell_companion-1.0.6.dist-info/METADATA
ovos_gui_plugin_shell_companion-1.0.6.dist-info/WHEEL
ovos_gui_plugin_shell_companion-1.0.6.dist-info/entry_points.txt
ovos_gui_plugin_shell_companion-1.0.6.dist-info/top_level.txt
ovos_gui_plugin_shell_companion-1.0.6.dist-info/zip-safe
ovos_gui_plugin_shell_companion-1.0.6.dist-info/RECORD
