Metadata-Version: 2.4
Name: ovos_gui_plugin_shell_companion
Version: 1.0.6
Summary: GUI plugin for ovos-shell
Home-page: https://github.com/OpenVoiceOS/ovos-gui-plugin-shell-companion
Author: Aiix
License: Apache-2.0
Classifier: Development Status :: 3 - Alpha
Classifier: Intended Audience :: Developers
Classifier: Topic :: Utilities
Classifier: License :: OSI Approved :: Apache Software License
Classifier: Programming Language :: Python :: 3.5
Classifier: Programming Language :: Python :: 3.6
Classifier: Programming Language :: Python :: 3.7
Classifier: Programming Language :: Python :: 3.8
Classifier: Programming Language :: Python :: 3.9
Classifier: Programming Language :: Python :: 3.10
License-File: LICENSE
Requires-Dist: ovos-plugin-manager<3.0.0,>=0.5.5
Requires-Dist: ovos-utils<1.0.0,>=0.0.34
Requires-Dist: ovos-bus-client<2.0.0,>=0.0.8
Requires-Dist: astral~=3.0
Dynamic: author
Dynamic: classifier
Dynamic: description
Dynamic: description-content-type
Dynamic: home-page
Dynamic: license
Dynamic: license-file
Dynamic: requires-dist
Dynamic: summary
